slack/__init__.py
slack/slack.py
slack_jamesstorm-0.0.4.dist-info/LICENSE
slack_jamesstorm-0.0.4.dist-info/METADATA
slack_jamesstorm-0.0.4.dist-info/WHEEL
slack_jamesstorm-0.0.4.dist-info/top_level.txt
slack_jamesstorm-0.0.4.dist-info/RECORD
